pytricia.cpython-313-x86_64-linux-gnu.so
pytricopelaje-1.2.0.dist-info/METADATA
pytricopelaje-1.2.0.dist-info/WHEEL
pytricopelaje-1.2.0.dist-info/top_level.txt
pytricopelaje-1.2.0.dist-info/RECORD
pytricopelaje-1.2.0.dist-info/licenses/COPYING
pytricopelaje-1.2.0.dist-info/licenses/COPYING.LESSER
