Metadata-Version: 2.4
Name: pytricopelaje
Version: 1.2.0
Summary: An efficient IP address storage and lookup module for Python.
Home-page: https://github.com/copelaje/pytricia
Author: Jeff Copeland
License: LGPL-3.0-or-later
Keywords: patricia tree,IP addresses
Classifier: Programming Language :: Python :: 2
Classifier: Programming Language :: Python :: 3
Classifier: Intended Audience :: Developers
Classifier: Operating System :: OS Independent
Classifier: Topic :: Software Development :: Libraries :: Python Modules
Classifier: Topic :: Internet :: Log Analysis
Classifier: Topic :: Scientific/Engineering
License-File: COPYING
License-File: COPYING.LESSER
Dynamic: author
Dynamic: classifier
Dynamic: description
Dynamic: home-page
Dynamic: keywords
Dynamic: license
Dynamic: license-file
Dynamic: summary
